{"nodes": [{"id": "c_healthai_app_assembly_engine_py", "label": "engine.py", "file_type": "code", "source_file": "C:\\HealthAI\\app\\assembly\\engine.py", "source_location": "L1"}, {"id": "assembly_engine_norm_value", "label": "_norm_value()", "file_type": "code", "source_file": "C:\\HealthAI\\app\\assembly\\engine.py", "source_location": "L78"}, {"id": "str", "label": "str", "file_type": "code", "source_file": "C:\\HealthAI\\app\\assembly\\engine.py", "source_location": "L78"}, {"id": "assembly_engine_caseassemblyengine", "label": "CaseAssemblyEngine", "file_type": "code", "source_file": "C:\\HealthAI\\app\\assembly\\engine.py", "source_location": "L86"}, {"id": "assembly_engine_caseassemblyengine_init", "label": ".__init__()", "file_type": "code", "source_file": "C:\\HealthAI\\app\\assembly\\engine.py", "source_location": "L89"}, {"id": "evidenceextractor", "label": "EvidenceExtractor", "file_type": "code", "source_file": "C:\\HealthAI\\app\\assembly\\engine.py", "source_location": "L89"}, {"id": "assembly_engine_caseassemblyengine_assemble", "label": ".assemble()", "file_type": "code", "source_file": "C:\\HealthAI\\app\\assembly\\engine.py", "source_location": "L92"}, {"id": "casedocument", "label": "CaseDocument", "file_type": "code", "source_file": "C:\\HealthAI\\app\\assembly\\engine.py", "source_location": "L92"}, {"id": "unifiedcasecontext", "label": "UnifiedCaseContext", "file_type": "code", "source_file": "C:\\HealthAI\\app\\assembly\\engine.py", "source_location": "L92"}, {"id": "assembly_engine_caseassemblyengine_synthesize_from_evidence", "label": ".synthesize_from_evidence()", "file_type": "code", "source_file": "C:\\HealthAI\\app\\assembly\\engine.py", "source_location": "L112"}, {"id": "evidencereference", "label": "EvidenceReference", "file_type": "code", "source_file": "C:\\HealthAI\\app\\assembly\\engine.py", "source_location": "L112"}, {"id": "assembly_engine_caseassemblyengine_assemble_from_evidence", "label": "._assemble_from_evidence()", "file_type": "code", "source_file": "C:\\HealthAI\\app\\assembly\\engine.py", "source_location": "L145"}, {"id": "bool", "label": "bool", "file_type": "code", "source_file": "C:\\HealthAI\\app\\assembly\\engine.py", "source_location": "L145"}, {"id": "assembly_engine_caseassemblyengine_heal_requested_service_evidence", "label": "._heal_requested_service_evidence()", "file_type": "code", "source_file": "C:\\HealthAI\\app\\assembly\\engine.py", "source_location": "L218"}, {"id": "assembly_engine_caseassemblyengine_dedupe", "label": "._dedupe()", "file_type": "code", "source_file": "C:\\HealthAI\\app\\assembly\\engine.py", "source_location": "L276"}, {"id": "assembly_engine_caseassemblyengine_value_of", "label": "._value_of()", "file_type": "code", "source_file": "C:\\HealthAI\\app\\assembly\\engine.py", "source_location": "L293"}, {"id": "assembly_engine_caseassemblyengine_distinct_values", "label": "._distinct_values()", "file_type": "code", "source_file": "C:\\HealthAI\\app\\assembly\\engine.py", "source_location": "L296"}, {"id": "assembly_engine_caseassemblyengine_display_values", "label": "._display_values()", "file_type": "code", "source_file": "C:\\HealthAI\\app\\assembly\\engine.py", "source_location": "L304"}, {"id": "assembly_engine_caseassemblyengine_choose", "label": "._choose()", "file_type": "code", "source_file": "C:\\HealthAI\\app\\assembly\\engine.py", "source_location": "L315"}, {"id": "assembly_engine_caseassemblyengine_synthesize_case", "label": "._synthesize_case()", "file_type": "code", "source_file": "C:\\HealthAI\\app\\assembly\\engine.py", "source_location": "L331"}, {"id": "resolvedfact", "label": "ResolvedFact", "file_type": "code", "source_file": "C:\\HealthAI\\app\\assembly\\engine.py", "source_location": "L331"}, {"id": "patientcase", "label": "PatientCase", "file_type": "code", "source_file": "C:\\HealthAI\\app\\assembly\\engine.py", "source_location": "L331"}, {"id": "assembly_engine_rationale_1", "label": "CaseAssemblyEngine: merge multi-document evidence into a unified context.  Res", "file_type": "rationale", "source_file": "C:\\HealthAI\\app\\assembly\\engine.py", "source_location": "L1"}, {"id": "assembly_engine_rationale_79", "label": "Normalize a value for equality comparison (case/space-insensitive).", "file_type": "rationale", "source_file": "C:\\HealthAI\\app\\assembly\\engine.py", "source_location": "L79"}, {"id": "assembly_engine_rationale_87", "label": "Assemble multiple CaseDocuments into a UnifiedCaseContext.", "file_type": "rationale", "source_file": "C:\\HealthAI\\app\\assembly\\engine.py", "source_location": "L87"}, {"id": "assembly_engine_rationale_95", "label": "Assemble a unified, evidence-backed context for a case.", "file_type": "rationale", "source_file": "C:\\HealthAI\\app\\assembly\\engine.py", "source_location": "L95"}, {"id": "assembly_engine_rationale_118", "label": "Assemble a context from a GIVEN evidence list (not re-extracted).          Mil", "file_type": "rationale", "source_file": "C:\\HealthAI\\app\\assembly\\engine.py", "source_location": "L118"}, {"id": "assembly_engine_rationale_153", "label": "Shared assembly core: group -> resolve -> synthesize a context.", "file_type": "rationale", "source_file": "C:\\HealthAI\\app\\assembly\\engine.py", "source_location": "L153"}, {"id": "assembly_engine_rationale_225", "label": "Add traceable requested-service evidence from known drug tokens.          The go", "file_type": "rationale", "source_file": "C:\\HealthAI\\app\\assembly\\engine.py", "source_location": "L225"}, {"id": "assembly_engine_rationale_277", "label": "Remove duplicate facts (same fact_type + value + document + page).", "file_type": "rationale", "source_file": "C:\\HealthAI\\app\\assembly\\engine.py", "source_location": "L277"}, {"id": "assembly_engine_rationale_321", "label": "Pick the best evidence for a fact: authoritative doc type, then conf.", "file_type": "rationale", "source_file": "C:\\HealthAI\\app\\assembly\\engine.py", "source_location": "L321"}, {"id": "assembly_engine_rationale_337", "label": "Build a PatientCase from resolved facts, attaching field sources.", "file_type": "rationale", "source_file": "C:\\HealthAI\\app\\assembly\\engine.py", "source_location": "L337"}], "edges": [{"source": "c_healthai_app_assembly_engine_py", "target": "app_evidence_extractor", "relation": "imports_from", "context": "import", "confidence": "EXTRACTED", "source_file": "C:\\HealthAI\\app\\assembly\\engine.py", "source_location": "L18", "weight": 1.0}, {"source": "c_healthai_app_assembly_engine_py", "target": "app_models_case_document", "relation": "imports_from", "context": "import", "confidence": "EXTRACTED", "source_file": "C:\\HealthAI\\app\\assembly\\engine.py", "source_location": "L19", "weight": 1.0}, {"source": "c_healthai_app_assembly_engine_py", "target": "app_models_conflict_report", "relation": "imports_from", "context": "import", "confidence": "EXTRACTED", "source_file": "C:\\HealthAI\\app\\assembly\\engine.py", "source_location": "L20", "weight": 1.0}, {"source": "c_healthai_app_assembly_engine_py", "target": "app_models_evidence_reference", "relation": "imports_from", "context": "import", "confidence": "EXTRACTED", "source_file": "C:\\HealthAI\\app\\assembly\\engine.py", "source_location": "L25", "weight": 1.0}, {"source": "c_healthai_app_assembly_engine_py", "target": "app_models_patient_case", "relation": "imports_from", "context": "import", "confidence": "EXTRACTED", "source_file": "C:\\HealthAI\\app\\assembly\\engine.py", "source_location": "L26", "weight": 1.0}, {"source": "c_healthai_app_assembly_engine_py", "target": "app_models_unified_case_context", "relation": "imports_from", "context": "import", "confidence": "EXTRACTED", "source_file": "C:\\HealthAI\\app\\assembly\\engine.py", "source_location": "L27", "weight": 1.0}, {"source": "c_healthai_app_assembly_engine_py", "target": "assembly_engine_norm_value", "relation": "contains", "confidence": "EXTRACTED", "source_file": "C:\\HealthAI\\app\\assembly\\engine.py", "source_location": "L78", "weight": 1.0}, {"source": "assembly_engine_norm_value", "target": "str", "relation": "references", "context": "parameter_type", "confidence": "EXTRACTED", "source_file": "C:\\HealthAI\\app\\assembly\\engine.py", "source_location": "L78", "weight": 1.0}, {"source": "assembly_engine_norm_value", "target": "str", "relation": "references", "context": "parameter_type", "confidence": "EXTRACTED", "source_file": "C:\\HealthAI\\app\\assembly\\engine.py", "source_location": "L78", "weight": 1.0}, {"source": "assembly_engine_norm_value", "target": "str", "relation": "references", "context": "return_type", "confidence": "EXTRACTED", "source_file": "C:\\HealthAI\\app\\assembly\\engine.py", "source_location": "L78", "weight": 1.0}, {"source": "c_healthai_app_assembly_engine_py", "target": "assembly_engine_caseassemblyengine", "relation": "contains", "confidence": "EXTRACTED", "source_file": "C:\\HealthAI\\app\\assembly\\engine.py", "source_location": "L86", "weight": 1.0}, {"source": "assembly_engine_caseassemblyengine", "target": "assembly_engine_caseassemblyengine_init", "relation": "method", "confidence": "EXTRACTED", "source_file": "C:\\HealthAI\\app\\assembly\\engine.py", "source_location": "L89", "weight": 1.0}, {"source": "assembly_engine_caseassemblyengine_init", "target": "evidenceextractor", "relation": "references", "context": "parameter_type", "confidence": "EXTRACTED", "source_file": "C:\\HealthAI\\app\\assembly\\engine.py", "source_location": "L89", "weight": 1.0}, {"source": "assembly_engine_caseassemblyengine", "target": "assembly_engine_caseassemblyengine_assemble", "relation": "method", "confidence": "EXTRACTED", "source_file": "C:\\HealthAI\\app\\assembly\\engine.py", "source_location": "L92", "weight": 1.0}, {"source": "assembly_engine_caseassemblyengine_assemble", "target": "str", "relation": "references", "context": "parameter_type", "confidence": "EXTRACTED", "source_file": "C:\\HealthAI\\app\\assembly\\engine.py", "source_location": "L92", "weight": 1.0}, {"source": "assembly_engine_caseassemblyengine_assemble", "target": "casedocument", "relation": "references", "context": "generic_arg", "confidence": "EXTRACTED", "source_file": "C:\\HealthAI\\app\\assembly\\engine.py", "source_location": "L92", "weight": 1.0}, {"source": "assembly_engine_caseassemblyengine_assemble", "target": "unifiedcasecontext", "relation": "references", "context": "return_type", "confidence": "EXTRACTED", "source_file": "C:\\HealthAI\\app\\assembly\\engine.py", "source_location": "L92", "weight": 1.0}, {"source": "assembly_engine_caseassemblyengine", "target": "assembly_engine_caseassemblyengine_synthesize_from_evidence", "relation": "method", "confidence": "EXTRACTED", "source_file": "C:\\HealthAI\\app\\assembly\\engine.py", "source_location": "L112", "weight": 1.0}, {"source": "assembly_engine_caseassemblyengine_synthesize_from_evidence", "target": "str", "relation": "references", "context": "parameter_type", "confidence": "EXTRACTED", "source_file": "C:\\HealthAI\\app\\assembly\\engine.py", "source_location": "L112", "weight": 1.0}, {"source": "assembly_engine_caseassemblyengine_synthesize_from_evidence", "target": "evidencereference", "relation": "references", "context": "generic_arg", "confidence": "EXTRACTED", "source_file": "C:\\HealthAI\\app\\assembly\\engine.py", "source_location": "L112", "weight": 1.0}, {"source": "assembly_engine_caseassemblyengine_synthesize_from_evidence", "target": "casedocument", "relation": "references", "context": "generic_arg", "confidence": "EXTRACTED", "source_file": "C:\\HealthAI\\app\\assembly\\engine.py", "source_location": "L112", "weight": 1.0}, {"source": "assembly_engine_caseassemblyengine_synthesize_from_evidence", "target": "unifiedcasecontext", "relation": "references", "context": "return_type", "confidence": "EXTRACTED", "source_file": "C:\\HealthAI\\app\\assembly\\engine.py", "source_location": "L112", "weight": 1.0}, {"source": "assembly_engine_caseassemblyengine", "target": "assembly_engine_caseassemblyengine_assemble_from_evidence", "relation": "method", "confidence": "EXTRACTED", "source_file": "C:\\HealthAI\\app\\assembly\\engine.py", "source_location": "L145", "weight": 1.0}, {"source": "assembly_engine_caseassemblyengine_assemble_from_evidence", "target": "str", "relation": "references", "context": "parameter_type", "confidence": "EXTRACTED", "source_file": "C:\\HealthAI\\app\\assembly\\engine.py", "source_location": "L145", "weight": 1.0}, {"source": "assembly_engine_caseassemblyengine_assemble_from_evidence", "target": "evidencereference", "relation": "references", "context": "generic_arg", "confidence": "EXTRACTED", "source_file": "C:\\HealthAI\\app\\assembly\\engine.py", "source_location": "L145", "weight": 1.0}, {"source": "assembly_engine_caseassemblyengine_assemble_from_evidence", "target": "str", "relation": "references", "context": "generic_arg", "confidence": "EXTRACTED", "source_file": "C:\\HealthAI\\app\\assembly\\engine.py", "source_location": "L145", "weight": 1.0}, {"source": "assembly_engine_caseassemblyengine_assemble_from_evidence", "target": "casedocument", "relation": "references", "context": "generic_arg", "confidence": "EXTRACTED", "source_file": "C:\\HealthAI\\app\\assembly\\engine.py", "source_location": "L145", "weight": 1.0}, {"source": "assembly_engine_caseassemblyengine_assemble_from_evidence", "target": "str", "relation": "references", "context": "generic_arg", "confidence": "EXTRACTED", "source_file": "C:\\HealthAI\\app\\assembly\\engine.py", "source_location": "L145", "weight": 1.0}, {"source": "assembly_engine_caseassemblyengine_assemble_from_evidence", "target": "bool", "relation": "references", "context": "parameter_type", "confidence": "EXTRACTED", "source_file": "C:\\HealthAI\\app\\assembly\\engine.py", "source_location": "L145", "weight": 1.0}, {"source": "assembly_engine_caseassemblyengine_assemble_from_evidence", "target": "unifiedcasecontext", "relation": "references", "context": "return_type", "confidence": "EXTRACTED", "source_file": "C:\\HealthAI\\app\\assembly\\engine.py", "source_location": "L145", "weight": 1.0}, {"source": "assembly_engine_caseassemblyengine", "target": "assembly_engine_caseassemblyengine_heal_requested_service_evidence", "relation": "method", "confidence": "EXTRACTED", "source_file": "C:\\HealthAI\\app\\assembly\\engine.py", "source_location": "L218", "weight": 1.0}, {"source": "assembly_engine_caseassemblyengine_heal_requested_service_evidence", "target": "str", "relation": "references", "context": "parameter_type", "confidence": "EXTRACTED", "source_file": "C:\\HealthAI\\app\\assembly\\engine.py", "source_location": "L218", "weight": 1.0}, {"source": "assembly_engine_caseassemblyengine_heal_requested_service_evidence", "target": "evidencereference", "relation": "references", "context": "generic_arg", "confidence": "EXTRACTED", "source_file": "C:\\HealthAI\\app\\assembly\\engine.py", "source_location": "L218", "weight": 1.0}, {"source": "assembly_engine_caseassemblyengine_heal_requested_service_evidence", "target": "str", "relation": "references", "context": "generic_arg", "confidence": "EXTRACTED", "source_file": "C:\\HealthAI\\app\\assembly\\engine.py", "source_location": "L218", "weight": 1.0}, {"source": "assembly_engine_caseassemblyengine_heal_requested_service_evidence", "target": "casedocument", "relation": "references", "context": "generic_arg", "confidence": "EXTRACTED", "source_file": "C:\\HealthAI\\app\\assembly\\engine.py", "source_location": "L218", "weight": 1.0}, {"source": "assembly_engine_caseassemblyengine_heal_requested_service_evidence", "target": "bool", "relation": "references", "context": "parameter_type", "confidence": "EXTRACTED", "source_file": "C:\\HealthAI\\app\\assembly\\engine.py", "source_location": "L218", "weight": 1.0}, {"source": "assembly_engine_caseassemblyengine_heal_requested_service_evidence", "target": "evidencereference", "relation": "references", "context": "generic_arg", "confidence": "EXTRACTED", "source_file": "C:\\HealthAI\\app\\assembly\\engine.py", "source_location": "L218", "weight": 1.0}, {"source": "assembly_engine_caseassemblyengine", "target": "assembly_engine_caseassemblyengine_dedupe", "relation": "method", "confidence": "EXTRACTED", "source_file": "C:\\HealthAI\\app\\assembly\\engine.py", "source_location": "L276", "weight": 1.0}, {"source": "assembly_engine_caseassemblyengine_dedupe", "target": "evidencereference", "relation": "references", "context": "generic_arg", "confidence": "EXTRACTED", "source_file": "C:\\HealthAI\\app\\assembly\\engine.py", "source_location": "L276", "weight": 1.0}, {"source": "assembly_engine_caseassemblyengine_dedupe", "target": "evidencereference", "relation": "references", "context": "generic_arg", "confidence": "EXTRACTED", "source_file": "C:\\HealthAI\\app\\assembly\\engine.py", "source_location": "L276", "weight": 1.0}, {"source": "assembly_engine_caseassemblyengine", "target": "assembly_engine_caseassemblyengine_value_of", "relation": "method", "confidence": "EXTRACTED", "source_file": "C:\\HealthAI\\app\\assembly\\engine.py", "source_location": "L293", "weight": 1.0}, {"source": "assembly_engine_caseassemblyengine_value_of", "target": "evidencereference", "relation": "references", "context": "parameter_type", "confidence": "EXTRACTED", "source_file": "C:\\HealthAI\\app\\assembly\\engine.py", "source_location": "L293", "weight": 1.0}, {"source": "assembly_engine_caseassemblyengine_value_of", "target": "str", "relation": "references", "context": "return_type", "confidence": "EXTRACTED", "source_file": "C:\\HealthAI\\app\\assembly\\engine.py", "source_location": "L293", "weight": 1.0}, {"source": "assembly_engine_caseassemblyengine", "target": "assembly_engine_caseassemblyengine_distinct_values", "relation": "method", "confidence": "EXTRACTED", "source_file": "C:\\HealthAI\\app\\assembly\\engine.py", "source_location": "L296", "weight": 1.0}, {"source": "assembly_engine_caseassemblyengine_distinct_values", "target": "str", "relation": "references", "context": "parameter_type", "confidence": "EXTRACTED", "source_file": "C:\\HealthAI\\app\\assembly\\engine.py", "source_location": "L296", "weight": 1.0}, {"source": "assembly_engine_caseassemblyengine_distinct_values", "target": "evidencereference", "relation": "references", "context": "generic_arg", "confidence": "EXTRACTED", "source_file": "C:\\HealthAI\\app\\assembly\\engine.py", "source_location": "L296", "weight": 1.0}, {"source": "assembly_engine_caseassemblyengine_distinct_values", "target": "str", "relation": "references", "context": "generic_arg", "confidence": "EXTRACTED", "source_file": "C:\\HealthAI\\app\\assembly\\engine.py", "source_location": "L296", "weight": 1.0}, {"source": "assembly_engine_caseassemblyengine", "target": "assembly_engine_caseassemblyengine_display_values", "relation": "method", "confidence": "EXTRACTED", "source_file": "C:\\HealthAI\\app\\assembly\\engine.py", "source_location": "L304", "weight": 1.0}, {"source": "assembly_engine_caseassemblyengine_display_values", "target": "str", "relation": "references", "context": "parameter_type", "confidence": "EXTRACTED", "source_file": "C:\\HealthAI\\app\\assembly\\engine.py", "source_location": "L304", "weight": 1.0}, {"source": "assembly_engine_caseassemblyengine_display_values", "target": "evidencereference", "relation": "references", "context": "generic_arg", "confidence": "EXTRACTED", "source_file": "C:\\HealthAI\\app\\assembly\\engine.py", "source_location": "L304", "weight": 1.0}, {"source": "assembly_engine_caseassemblyengine_display_values", "target": "str", "relation": "references", "context": "generic_arg", "confidence": "EXTRACTED", "source_file": "C:\\HealthAI\\app\\assembly\\engine.py", "source_location": "L304", "weight": 1.0}, {"source": "assembly_engine_caseassemblyengine", "target": "assembly_engine_caseassemblyengine_choose", "relation": "method", "confidence": "EXTRACTED", "source_file": "C:\\HealthAI\\app\\assembly\\engine.py", "source_location": "L315", "weight": 1.0}, {"source": "assembly_engine_caseassemblyengine_choose", "target": "str", "relation": "references", "context": "parameter_type", "confidence": "EXTRACTED", "source_file": "C:\\HealthAI\\app\\assembly\\engine.py", "source_location": "L315", "weight": 1.0}, {"source": "assembly_engine_caseassemblyengine_choose", "target": "evidencereference", "relation": "references", "context": "generic_arg", "confidence": "EXTRACTED", "source_file": "C:\\HealthAI\\app\\assembly\\engine.py", "source_location": "L315", "weight": 1.0}, {"source": "assembly_engine_caseassemblyengine_choose", "target": "str", "relation": "references", "context": "generic_arg", "confidence": "EXTRACTED", "source_file": "C:\\HealthAI\\app\\assembly\\engine.py", "source_location": "L315", "weight": 1.0}, {"source": "assembly_engine_caseassemblyengine_choose", "target": "casedocument", "relation": "references", "context": "generic_arg", "confidence": "EXTRACTED", "source_file": "C:\\HealthAI\\app\\assembly\\engine.py", "source_location": "L315", "weight": 1.0}, {"source": "assembly_engine_caseassemblyengine_choose", "target": "evidencereference", "relation": "references", "context": "return_type", "confidence": "EXTRACTED", "source_file": "C:\\HealthAI\\app\\assembly\\engine.py", "source_location": "L315", "weight": 1.0}, {"source": "assembly_engine_caseassemblyengine", "target": "assembly_engine_caseassemblyengine_synthesize_case", "relation": "method", "confidence": "EXTRACTED", "source_file": "C:\\HealthAI\\app\\assembly\\engine.py", "source_location": "L331", "weight": 1.0}, {"source": "assembly_engine_caseassemblyengine_synthesize_case", "target": "str", "relation": "references", "context": "parameter_type", "confidence": "EXTRACTED", "source_file": "C:\\HealthAI\\app\\assembly\\engine.py", "source_location": "L331", "weight": 1.0}, {"source": "assembly_engine_caseassemblyengine_synthesize_case", "target": "str", "relation": "references", "context": "generic_arg", "confidence": "EXTRACTED", "source_file": "C:\\HealthAI\\app\\assembly\\engine.py", "source_location": "L331", "weight": 1.0}, {"source": "assembly_engine_caseassemblyengine_synthesize_case", "target": "resolvedfact", "relation": "references", "context": "generic_arg", "confidence": "EXTRACTED", "source_file": "C:\\HealthAI\\app\\assembly\\engine.py", "source_location": "L331", "weight": 1.0}, {"source": "assembly_engine_caseassemblyengine_synthesize_case", "target": "str", "relation": "references", "context": "generic_arg", "confidence": "EXTRACTED", "source_file": "C:\\HealthAI\\app\\assembly\\engine.py", "source_location": "L331", "weight": 1.0}, {"source": "assembly_engine_caseassemblyengine_synthesize_case", "target": "evidencereference", "relation": "references", "context": "generic_arg", "confidence": "EXTRACTED", "source_file": "C:\\HealthAI\\app\\assembly\\engine.py", "source_location": "L331", "weight": 1.0}, {"source": "assembly_engine_caseassemblyengine_synthesize_case", "target": "patientcase", "relation": "references", "context": "return_type", "confidence": "EXTRACTED", "source_file": "C:\\HealthAI\\app\\assembly\\engine.py", "source_location": "L331", "weight": 1.0}, {"source": "assembly_engine_caseassemblyengine_init", "target": "evidenceextractor", "relation": "calls", "context": "call", "confidence": "EXTRACTED", "source_file": "C:\\HealthAI\\app\\assembly\\engine.py", "source_location": "L90", "weight": 1.0}, {"source": "assembly_engine_caseassemblyengine_assemble", "target": "assembly_engine_caseassemblyengine_dedupe", "relation": "calls", "context": "call", "confidence": "EXTRACTED", "source_file": "C:\\HealthAI\\app\\assembly\\engine.py", "source_location": "L102", "weight": 1.0}, {"source": "assembly_engine_caseassemblyengine_assemble", "target": "assembly_engine_caseassemblyengine_assemble_from_evidence", "relation": "calls", "context": "call", "confidence": "EXTRACTED", "source_file": "C:\\HealthAI\\app\\assembly\\engine.py", "source_location": "L104", "weight": 1.0}, {"source": "assembly_engine_caseassemblyengine_synthesize_from_evidence", "target": "assembly_engine_caseassemblyengine_dedupe", "relation": "calls", "context": "call", "confidence": "EXTRACTED", "source_file": "C:\\HealthAI\\app\\assembly\\engine.py", "source_location": "L132", "weight": 1.0}, {"source": "assembly_engine_caseassemblyengine_synthesize_from_evidence", "target": "assembly_engine_caseassemblyengine_assemble_from_evidence", "relation": "calls", "context": "call", "confidence": "EXTRACTED", "source_file": "C:\\HealthAI\\app\\assembly\\engine.py", "source_location": "L137", "weight": 1.0}, {"source": "assembly_engine_caseassemblyengine_assemble_from_evidence", "target": "assembly_engine_caseassemblyengine_heal_requested_service_evidence", "relation": "calls", "context": "call", "confidence": "EXTRACTED", "source_file": "C:\\HealthAI\\app\\assembly\\engine.py", "source_location": "L154", "weight": 1.0}, {"source": "assembly_engine_caseassemblyengine_assemble_from_evidence", "target": "assembly_engine_caseassemblyengine_distinct_values", "relation": "calls", "context": "call", "confidence": "EXTRACTED", "source_file": "C:\\HealthAI\\app\\assembly\\engine.py", "source_location": "L171", "weight": 1.0}, {"source": "assembly_engine_caseassemblyengine_assemble_from_evidence", "target": "assembly_engine_caseassemblyengine_choose", "relation": "calls", "context": "call", "confidence": "EXTRACTED", "source_file": "C:\\HealthAI\\app\\assembly\\engine.py", "source_location": "L172", "weight": 1.0}, {"source": "assembly_engine_caseassemblyengine_assemble_from_evidence", "target": "resolvedfact", "relation": "calls", "context": "call", "confidence": "EXTRACTED", "source_file": "C:\\HealthAI\\app\\assembly\\engine.py", "source_location": "L173", "weight": 1.0}, {"source": "assembly_engine_caseassemblyengine_assemble_from_evidence", "target": "assembly_engine_norm_value", "relation": "calls", "context": "call", "confidence": "EXTRACTED", "source_file": "C:\\HealthAI\\app\\assembly\\engine.py", "source_location": "L179", "weight": 1.0}, {"source": "assembly_engine_caseassemblyengine_assemble_from_evidence", "target": "assembly_engine_caseassemblyengine_display_values", "relation": "calls", "context": "call", "confidence": "EXTRACTED", "source_file": "C:\\HealthAI\\app\\assembly\\engine.py", "source_location": "L187", "weight": 1.0}, {"source": "assembly_engine_caseassemblyengine_assemble_from_evidence", "target": "assembly_engine_caseassemblyengine_synthesize_case", "relation": "calls", "context": "call", "confidence": "EXTRACTED", "source_file": "C:\\HealthAI\\app\\assembly\\engine.py", "source_location": "L206", "weight": 1.0}, {"source": "assembly_engine_caseassemblyengine_assemble_from_evidence", "target": "unifiedcasecontext", "relation": "calls", "context": "call", "confidence": "EXTRACTED", "source_file": "C:\\HealthAI\\app\\assembly\\engine.py", "source_location": "L208", "weight": 1.0}, {"source": "assembly_engine_caseassemblyengine_heal_requested_service_evidence", "target": "evidencereference", "relation": "calls", "context": "call", "confidence": "EXTRACTED", "source_file": "C:\\HealthAI\\app\\assembly\\engine.py", "source_location": "L257", "weight": 1.0}, {"source": "assembly_engine_caseassemblyengine_dedupe", "target": "assembly_engine_norm_value", "relation": "calls", "context": "call", "confidence": "EXTRACTED", "source_file": "C:\\HealthAI\\app\\assembly\\engine.py", "source_location": "L283", "weight": 1.0}, {"source": "assembly_engine_caseassemblyengine_distinct_values", "target": "assembly_engine_norm_value", "relation": "calls", "context": "call", "confidence": "EXTRACTED", "source_file": "C:\\HealthAI\\app\\assembly\\engine.py", "source_location": "L299", "weight": 1.0}, {"source": "assembly_engine_caseassemblyengine_distinct_values", "target": "assembly_engine_caseassemblyengine_value_of", "relation": "calls", "context": "call", "confidence": "EXTRACTED", "source_file": "C:\\HealthAI\\app\\assembly\\engine.py", "source_location": "L299", "weight": 1.0}, {"source": "assembly_engine_caseassemblyengine_display_values", "target": "assembly_engine_caseassemblyengine_value_of", "relation": "calls", "context": "call", "confidence": "EXTRACTED", "source_file": "C:\\HealthAI\\app\\assembly\\engine.py", "source_location": "L308", "weight": 1.0}, {"source": "assembly_engine_caseassemblyengine_display_values", "target": "assembly_engine_norm_value", "relation": "calls", "context": "call", "confidence": "EXTRACTED", "source_file": "C:\\HealthAI\\app\\assembly\\engine.py", "source_location": "L309", "weight": 1.0}, {"source": "assembly_engine_caseassemblyengine_synthesize_case", "target": "patientcase", "relation": "calls", "context": "call", "confidence": "EXTRACTED", "source_file": "C:\\HealthAI\\app\\assembly\\engine.py", "source_location": "L362", "weight": 1.0}, {"source": "assembly_engine_rationale_1", "target": "c_healthai_app_assembly_engine_py", "relation": "rationale_for", "confidence": "EXTRACTED", "source_file": "C:\\HealthAI\\app\\assembly\\engine.py", "source_location": "L1", "weight": 1.0}, {"source": "assembly_engine_rationale_79", "target": "assembly_engine_norm_value", "relation": "rationale_for", "confidence": "EXTRACTED", "source_file": "C:\\HealthAI\\app\\assembly\\engine.py", "source_location": "L79", "weight": 1.0}, {"source": "assembly_engine_rationale_87", "target": "assembly_engine_caseassemblyengine", "relation": "rationale_for", "confidence": "EXTRACTED", "source_file": "C:\\HealthAI\\app\\assembly\\engine.py", "source_location": "L87", "weight": 1.0}, {"source": "assembly_engine_rationale_95", "target": "assembly_engine_caseassemblyengine_assemble", "relation": "rationale_for", "confidence": "EXTRACTED", "source_file": "C:\\HealthAI\\app\\assembly\\engine.py", "source_location": "L95", "weight": 1.0}, {"source": "assembly_engine_rationale_118", "target": "assembly_engine_caseassemblyengine_synthesize_from_evidence", "relation": "rationale_for", "confidence": "EXTRACTED", "source_file": "C:\\HealthAI\\app\\assembly\\engine.py", "source_location": "L118", "weight": 1.0}, {"source": "assembly_engine_rationale_153", "target": "assembly_engine_caseassemblyengine_assemble_from_evidence", "relation": "rationale_for", "confidence": "EXTRACTED", "source_file": "C:\\HealthAI\\app\\assembly\\engine.py", "source_location": "L153", "weight": 1.0}, {"source": "assembly_engine_rationale_225", "target": "assembly_engine_caseassemblyengine_heal_requested_service_evidence", "relation": "rationale_for", "confidence": "EXTRACTED", "source_file": "C:\\HealthAI\\app\\assembly\\engine.py", "source_location": "L225", "weight": 1.0}, {"source": "assembly_engine_rationale_277", "target": "assembly_engine_caseassemblyengine_dedupe", "relation": "rationale_for", "confidence": "EXTRACTED", "source_file": "C:\\HealthAI\\app\\assembly\\engine.py", "source_location": "L277", "weight": 1.0}, {"source": "assembly_engine_rationale_321", "target": "assembly_engine_caseassemblyengine_choose", "relation": "rationale_for", "confidence": "EXTRACTED", "source_file": "C:\\HealthAI\\app\\assembly\\engine.py", "source_location": "L321", "weight": 1.0}, {"source": "assembly_engine_rationale_337", "target": "assembly_engine_caseassemblyengine_synthesize_case", "relation": "rationale_for", "confidence": "EXTRACTED", "source_file": "C:\\HealthAI\\app\\assembly\\engine.py", "source_location": "L337", "weight": 1.0}], "raw_calls": [{"caller_nid": "assembly_engine_norm_value", "callee": "join", "is_member_call": true, "source_file": "C:\\HealthAI\\app\\assembly\\engine.py", "source_location": "L80"}, {"caller_nid": "assembly_engine_norm_value", "callee": "split", "is_member_call": true, "source_file": "C:\\HealthAI\\app\\assembly\\engine.py", "source_location": "L80"}, {"caller_nid": "assembly_engine_norm_value", "callee": "strip", "is_member_call": true, "source_file": "C:\\HealthAI\\app\\assembly\\engine.py", "source_location": "L80"}, {"caller_nid": "assembly_engine_norm_value", "callee": "upper", "is_member_call": true, "source_file": "C:\\HealthAI\\app\\assembly\\engine.py", "source_location": "L82"}, {"caller_nid": "assembly_engine_norm_value", "callee": "lower", "is_member_call": true, "source_file": "C:\\HealthAI\\app\\assembly\\engine.py", "source_location": "L83"}, {"caller_nid": "assembly_engine_caseassemblyengine_assemble", "callee": "extend", "is_member_call": true, "source_file": "C:\\HealthAI\\app\\assembly\\engine.py", "source_location": "L101"}, {"caller_nid": "assembly_engine_caseassemblyengine_assemble", "callee": "extract", "is_member_call": true, "source_file": "C:\\HealthAI\\app\\assembly\\engine.py", "source_location": "L101"}, {"caller_nid": "assembly_engine_caseassemblyengine_synthesize_from_evidence", "callee": "append", "is_member_call": true, "source_file": "C:\\HealthAI\\app\\assembly\\engine.py", "source_location": "L136"}, {"caller_nid": "assembly_engine_caseassemblyengine_assemble_from_evidence", "callee": "append", "is_member_call": true, "source_file": "C:\\HealthAI\\app\\assembly\\engine.py", "source_location": "L161"}, {"caller_nid": "assembly_engine_caseassemblyengine_assemble_from_evidence", "callee": "setdefault", "is_member_call": true, "source_file": "C:\\HealthAI\\app\\assembly\\engine.py", "source_location": "L161"}, {"caller_nid": "assembly_engine_caseassemblyengine_assemble_from_evidence", "callee": "get", "is_member_call": true, "source_file": "C:\\HealthAI\\app\\assembly\\engine.py", "source_location": "L168"}, {"caller_nid": "assembly_engine_caseassemblyengine_assemble_from_evidence", "callee": "split", "is_member_call": true, "source_file": "C:\\HealthAI\\app\\assembly\\engine.py", "source_location": "L175"}, {"caller_nid": "assembly_engine_caseassemblyengine_assemble_from_evidence", "callee": "split", "is_member_call": true, "source_file": "C:\\HealthAI\\app\\assembly\\engine.py", "source_location": "L179"}, {"caller_nid": "assembly_engine_caseassemblyengine_assemble_from_evidence", "callee": "append", "is_member_call": true, "source_file": "C:\\HealthAI\\app\\assembly\\engine.py", "source_location": "L182"}, {"caller_nid": "assembly_engine_caseassemblyengine_assemble_from_evidence", "callee": "FactConflict", "is_member_call": false, "source_file": "C:\\HealthAI\\app\\assembly\\engine.py", "source_location": "L183"}, {"caller_nid": "assembly_engine_caseassemblyengine_assemble_from_evidence", "callee": "get", "is_member_call": true, "source_file": "C:\\HealthAI\\app\\assembly\\engine.py", "source_location": "L186"}, {"caller_nid": "assembly_engine_caseassemblyengine_assemble_from_evidence", "callee": "join", "is_member_call": true, "source_file": "C:\\HealthAI\\app\\assembly\\engine.py", "source_location": "L191"}, {"caller_nid": "assembly_engine_caseassemblyengine_assemble_from_evidence", "callee": "ConflictReport", "is_member_call": false, "source_file": "C:\\HealthAI\\app\\assembly\\engine.py", "source_location": "L203"}, {"caller_nid": "assembly_engine_caseassemblyengine_heal_requested_service_evidence", "callee": "join", "is_member_call": true, "source_file": "C:\\HealthAI\\app\\assembly\\engine.py", "source_location": "L235"}, {"caller_nid": "assembly_engine_caseassemblyengine_heal_requested_service_evidence", "callee": "append", "is_member_call": true, "source_file": "C:\\HealthAI\\app\\assembly\\engine.py", "source_location": "L239"}, {"caller_nid": "assembly_engine_caseassemblyengine_heal_requested_service_evidence", "callee": "values", "is_member_call": true, "source_file": "C:\\HealthAI\\app\\assembly\\engine.py", "source_location": "L242"}, {"caller_nid": "assembly_engine_caseassemblyengine_heal_requested_service_evidence", "callee": "pages", "is_member_call": true, "source_file": "C:\\HealthAI\\app\\assembly\\engine.py", "source_location": "L243"}, {"caller_nid": "assembly_engine_caseassemblyengine_heal_requested_service_evidence", "callee": "splitlines", "is_member_call": true, "source_file": "C:\\HealthAI\\app\\assembly\\engine.py", "source_location": "L244"}, {"caller_nid": "assembly_engine_caseassemblyengine_heal_requested_service_evidence", "callee": "strip", "is_member_call": true, "source_file": "C:\\HealthAI\\app\\assembly\\engine.py", "source_location": "L245"}, {"caller_nid": "assembly_engine_caseassemblyengine_heal_requested_service_evidence", "callee": "append", "is_member_call": true, "source_file": "C:\\HealthAI\\app\\assembly\\engine.py", "source_location": "L246"}, {"caller_nid": "assembly_engine_caseassemblyengine_heal_requested_service_evidence", "callee": "strip", "is_member_call": true, "source_file": "C:\\HealthAI\\app\\assembly\\engine.py", "source_location": "L246"}, {"caller_nid": "assembly_engine_caseassemblyengine_heal_requested_service_evidence", "callee": "lower", "is_member_call": true, "source_file": "C:\\HealthAI\\app\\assembly\\engine.py", "source_location": "L249"}, {"caller_nid": "assembly_engine_caseassemblyengine_heal_requested_service_evidence", "callee": "get", "is_member_call": true, "source_file": "C:\\HealthAI\\app\\assembly\\engine.py", "source_location": "L254"}, {"caller_nid": "assembly_engine_caseassemblyengine_dedupe", "callee": "split", "is_member_call": true, "source_file": "C:\\HealthAI\\app\\assembly\\engine.py", "source_location": "L283"}, {"caller_nid": "assembly_engine_caseassemblyengine_dedupe", "callee": "add", "is_member_call": true, "source_file": "C:\\HealthAI\\app\\assembly\\engine.py", "source_location": "L288"}, {"caller_nid": "assembly_engine_caseassemblyengine_dedupe", "callee": "append", "is_member_call": true, "source_file": "C:\\HealthAI\\app\\assembly\\engine.py", "source_location": "L289"}, {"caller_nid": "assembly_engine_caseassemblyengine_value_of", "callee": "split", "is_member_call": true, "source_file": "C:\\HealthAI\\app\\assembly\\engine.py", "source_location": "L294"}, {"caller_nid": "assembly_engine_caseassemblyengine_distinct_values", "callee": "append", "is_member_call": true, "source_file": "C:\\HealthAI\\app\\assembly\\engine.py", "source_location": "L301"}, {"caller_nid": "assembly_engine_caseassemblyengine_display_values", "callee": "add", "is_member_call": true, "source_file": "C:\\HealthAI\\app\\assembly\\engine.py", "source_location": "L311"}, {"caller_nid": "assembly_engine_caseassemblyengine_display_values", "callee": "append", "is_member_call": true, "source_file": "C:\\HealthAI\\app\\assembly\\engine.py", "source_location": "L312"}, {"caller_nid": "assembly_engine_caseassemblyengine_display_values", "callee": "citation", "is_member_call": true, "source_file": "C:\\HealthAI\\app\\assembly\\engine.py", "source_location": "L312"}, {"caller_nid": "assembly_engine_caseassemblyengine_choose", "callee": "get", "is_member_call": true, "source_file": "C:\\HealthAI\\app\\assembly\\engine.py", "source_location": "L322"}, {"caller_nid": "assembly_engine_caseassemblyengine_synthesize_case", "callee": "val", "is_member_call": false, "source_file": "C:\\HealthAI\\app\\assembly\\engine.py", "source_location": "L352"}, {"caller_nid": "assembly_engine_caseassemblyengine_synthesize_case", "callee": "items", "is_member_call": true, "source_file": "C:\\HealthAI\\app\\assembly\\engine.py", "source_location": "L355"}, {"caller_nid": "assembly_engine_caseassemblyengine_synthesize_case", "callee": "FieldSource", "is_member_call": false, "source_file": "C:\\HealthAI\\app\\assembly\\engine.py", "source_location": "L356"}, {"caller_nid": "assembly_engine_caseassemblyengine_synthesize_case", "callee": "val", "is_member_call": false, "source_file": "C:\\HealthAI\\app\\assembly\\engine.py", "source_location": "L363"}, {"caller_nid": "assembly_engine_caseassemblyengine_synthesize_case", "callee": "val", "is_member_call": false, "source_file": "C:\\HealthAI\\app\\assembly\\engine.py", "source_location": "L364"}, {"caller_nid": "assembly_engine_caseassemblyengine_synthesize_case", "callee": "val", "is_member_call": false, "source_file": "C:\\HealthAI\\app\\assembly\\engine.py", "source_location": "L365"}, {"caller_nid": "assembly_engine_caseassemblyengine_synthesize_case", "callee": "val", "is_member_call": false, "source_file": "C:\\HealthAI\\app\\assembly\\engine.py", "source_location": "L366"}, {"caller_nid": "assembly_engine_caseassemblyengine_synthesize_case", "callee": "codes", "is_member_call": false, "source_file": "C:\\HealthAI\\app\\assembly\\engine.py", "source_location": "L367"}, {"caller_nid": "assembly_engine_caseassemblyengine_synthesize_case", "callee": "val", "is_member_call": false, "source_file": "C:\\HealthAI\\app\\assembly\\engine.py", "source_location": "L368"}, {"caller_nid": "assembly_engine_caseassemblyengine_synthesize_case", "callee": "codes", "is_member_call": false, "source_file": "C:\\HealthAI\\app\\assembly\\engine.py", "source_location": "L369"}, {"caller_nid": "assembly_engine_caseassemblyengine_synthesize_case", "callee": "val", "is_member_call": false, "source_file": "C:\\HealthAI\\app\\assembly\\engine.py", "source_location": "L370"}, {"caller_nid": "assembly_engine_caseassemblyengine_synthesize_case", "callee": "val", "is_member_call": false, "source_file": "C:\\HealthAI\\app\\assembly\\engine.py", "source_location": "L372"}, {"caller_nid": "assembly_engine_caseassemblyengine_synthesize_case", "callee": "val", "is_member_call": false, "source_file": "C:\\HealthAI\\app\\assembly\\engine.py", "source_location": "L373"}]}