{"nodes": [{"id": "c_healthai_app_ocr_placeholder_py", "label": "placeholder.py", "file_type": "code", "source_file": "C:\\HealthAI\\app\\ocr\\placeholder.py", "source_location": "L1"}, {"id": "ocr_placeholder_placeholderocrengine", "label": "PlaceholderOCREngine", "file_type": "code", "source_file": "C:\\HealthAI\\app\\ocr\\placeholder.py", "source_location": "L22"}, {"id": "ocrengine", "label": "OCREngine", "file_type": "code", "source_file": "", "source_location": ""}, {"id": "ocr_placeholder_placeholderocrengine_is_available", "label": ".is_available()", "file_type": "code", "source_file": "C:\\HealthAI\\app\\ocr\\placeholder.py", "source_location": "L28"}, {"id": "bool", "label": "bool", "file_type": "code", "source_file": "C:\\HealthAI\\app\\ocr\\placeholder.py", "source_location": "L28"}, {"id": "ocr_placeholder_placeholderocrengine_capabilities", "label": ".capabilities()", "file_type": "code", "source_file": "C:\\HealthAI\\app\\ocr\\placeholder.py", "source_location": "L32"}, {"id": "ocrcapability", "label": "OCRCapability", "file_type": "code", "source_file": "C:\\HealthAI\\app\\ocr\\placeholder.py", "source_location": "L32"}, {"id": "ocr_placeholder_placeholderocrengine_unavailable", "label": "._unavailable()", "file_type": "code", "source_file": "C:\\HealthAI\\app\\ocr\\placeholder.py", "source_location": "L37"}, {"id": "ocrresult", "label": "OCRResult", "file_type": "code", "source_file": "C:\\HealthAI\\app\\ocr\\placeholder.py", "source_location": "L37"}, {"id": "ocr_placeholder_placeholderocrengine_recognize_image", "label": ".recognize_image()", "file_type": "code", "source_file": "C:\\HealthAI\\app\\ocr\\placeholder.py", "source_location": "L44"}, {"id": "bytes", "label": "bytes", "file_type": "code", "source_file": "C:\\HealthAI\\app\\ocr\\placeholder.py", "source_location": "L44"}, {"id": "str", "label": "str", "file_type": "code", "source_file": "C:\\HealthAI\\app\\ocr\\placeholder.py", "source_location": "L44"}, {"id": "ocr_placeholder_placeholderocrengine_recognize_pdf", "label": ".recognize_pdf()", "file_type": "code", "source_file": "C:\\HealthAI\\app\\ocr\\placeholder.py", "source_location": "L47"}, {"id": "ocr_placeholder_rationale_1", "label": "Placeholder OCR engine.  A no-op implementation of :class:`OCREngine` that exi", "file_type": "rationale", "source_file": "C:\\HealthAI\\app\\ocr\\placeholder.py", "source_location": "L1"}, {"id": "ocr_placeholder_rationale_23", "label": "A non-functional OCR engine used as an architectural placeholder.", "file_type": "rationale", "source_file": "C:\\HealthAI\\app\\ocr\\placeholder.py", "source_location": "L23"}], "edges": [{"source": "c_healthai_app_ocr_placeholder_py", "target": "app_ocr_base", "relation": "imports_from", "context": "import", "confidence": "EXTRACTED", "source_file": "C:\\HealthAI\\app\\ocr\\placeholder.py", "source_location": "L14", "weight": 1.0}, {"source": "c_healthai_app_ocr_placeholder_py", "target": "ocr_placeholder_placeholderocrengine", "relation": "contains", "confidence": "EXTRACTED", "source_file": "C:\\HealthAI\\app\\ocr\\placeholder.py", "source_location": "L22", "weight": 1.0}, {"source": "ocr_placeholder_placeholderocrengine", "target": "ocrengine", "relation": "inherits", "confidence": "EXTRACTED", "source_file": "C:\\HealthAI\\app\\ocr\\placeholder.py", "source_location": "L22", "weight": 1.0}, {"source": "ocr_placeholder_placeholderocrengine", "target": "ocr_placeholder_placeholderocrengine_is_available", "relation": "method", "confidence": "EXTRACTED", "source_file": "C:\\HealthAI\\app\\ocr\\placeholder.py", "source_location": "L28", "weight": 1.0}, {"source": "ocr_placeholder_placeholderocrengine_is_available", "target": "bool", "relation": "references", "context": "return_type", "confidence": "EXTRACTED", "source_file": "C:\\HealthAI\\app\\ocr\\placeholder.py", "source_location": "L28", "weight": 1.0}, {"source": "ocr_placeholder_placeholderocrengine", "target": "ocr_placeholder_placeholderocrengine_capabilities", "relation": "method", "confidence": "EXTRACTED", "source_file": "C:\\HealthAI\\app\\ocr\\placeholder.py", "source_location": "L32", "weight": 1.0}, {"source": "ocr_placeholder_placeholderocrengine_capabilities", "target": "ocrcapability", "relation": "references", "context": "generic_arg", "confidence": "EXTRACTED", "source_file": "C:\\HealthAI\\app\\ocr\\placeholder.py", "source_location": "L32", "weight": 1.0}, {"source": "ocr_placeholder_placeholderocrengine", "target": "ocr_placeholder_placeholderocrengine_unavailable", "relation": "method", "confidence": "EXTRACTED", "source_file": "C:\\HealthAI\\app\\ocr\\placeholder.py", "source_location": "L37", "weight": 1.0}, {"source": "ocr_placeholder_placeholderocrengine_unavailable", "target": "ocrresult", "relation": "references", "context": "return_type", "confidence": "EXTRACTED", "source_file": "C:\\HealthAI\\app\\ocr\\placeholder.py", "source_location": "L37", "weight": 1.0}, {"source": "ocr_placeholder_placeholderocrengine", "target": "ocr_placeholder_placeholderocrengine_recognize_image", "relation": "method", "confidence": "EXTRACTED", "source_file": "C:\\HealthAI\\app\\ocr\\placeholder.py", "source_location": "L44", "weight": 1.0}, {"source": "ocr_placeholder_placeholderocrengine_recognize_image", "target": "bytes", "relation": "references", "context": "parameter_type", "confidence": "EXTRACTED", "source_file": "C:\\HealthAI\\app\\ocr\\placeholder.py", "source_location": "L44", "weight": 1.0}, {"source": "ocr_placeholder_placeholderocrengine_recognize_image", "target": "str", "relation": "references", "context": "parameter_type", "confidence": "EXTRACTED", "source_file": "C:\\HealthAI\\app\\ocr\\placeholder.py", "source_location": "L44", "weight": 1.0}, {"source": "ocr_placeholder_placeholderocrengine_recognize_image", "target": "ocrresult", "relation": "references", "context": "return_type", "confidence": "EXTRACTED", "source_file": "C:\\HealthAI\\app\\ocr\\placeholder.py", "source_location": "L44", "weight": 1.0}, {"source": "ocr_placeholder_placeholderocrengine", "target": "ocr_placeholder_placeholderocrengine_recognize_pdf", "relation": "method", "confidence": "EXTRACTED", "source_file": "C:\\HealthAI\\app\\ocr\\placeholder.py", "source_location": "L47", "weight": 1.0}, {"source": "ocr_placeholder_placeholderocrengine_recognize_pdf", "target": "bytes", "relation": "references", "context": "parameter_type", "confidence": "EXTRACTED", "source_file": "C:\\HealthAI\\app\\ocr\\placeholder.py", "source_location": "L47", "weight": 1.0}, {"source": "ocr_placeholder_placeholderocrengine_recognize_pdf", "target": "str", "relation": "references", "context": "parameter_type", "confidence": "EXTRACTED", "source_file": "C:\\HealthAI\\app\\ocr\\placeholder.py", "source_location": "L47", "weight": 1.0}, {"source": "ocr_placeholder_placeholderocrengine_recognize_pdf", "target": "ocrresult", "relation": "references", "context": "return_type", "confidence": "EXTRACTED", "source_file": "C:\\HealthAI\\app\\ocr\\placeholder.py", "source_location": "L47", "weight": 1.0}, {"source": "ocr_placeholder_placeholderocrengine_recognize_image", "target": "ocr_placeholder_placeholderocrengine_unavailable", "relation": "calls", "context": "call", "confidence": "EXTRACTED", "source_file": "C:\\HealthAI\\app\\ocr\\placeholder.py", "source_location": "L45", "weight": 1.0}, {"source": "ocr_placeholder_placeholderocrengine_recognize_pdf", "target": "ocr_placeholder_placeholderocrengine_unavailable", "relation": "calls", "context": "call", "confidence": "EXTRACTED", "source_file": "C:\\HealthAI\\app\\ocr\\placeholder.py", "source_location": "L48", "weight": 1.0}, {"source": "ocr_placeholder_rationale_1", "target": "c_healthai_app_ocr_placeholder_py", "relation": "rationale_for", "confidence": "EXTRACTED", "source_file": "C:\\HealthAI\\app\\ocr\\placeholder.py", "source_location": "L1", "weight": 1.0}, {"source": "ocr_placeholder_rationale_23", "target": "ocr_placeholder_placeholderocrengine", "relation": "rationale_for", "confidence": "EXTRACTED", "source_file": "C:\\HealthAI\\app\\ocr\\placeholder.py", "source_location": "L23", "weight": 1.0}], "raw_calls": [{"caller_nid": "ocr_placeholder_placeholderocrengine_unavailable", "callee": "OCRNotAvailableError", "is_member_call": false, "source_file": "C:\\HealthAI\\app\\ocr\\placeholder.py", "source_location": "L38"}]}